LICENSE.txt
README.md
setup.py
YekongLib/__init__.py
YekongLib.egg-info/PKG-INFO
YekongLib.egg-info/SOURCES.txt
YekongLib.egg-info/dependency_links.txt
YekongLib.egg-info/requires.txt
YekongLib.egg-info/top_level.txt
YekongLib/Crypto/Base16.py
YekongLib/Crypto/Base32.py
YekongLib/Crypto/Base64.py
YekongLib/Crypto/__init__.py
YekongLib/Crypto/Asymmetric/__init__.py
YekongLib/Crypto/Hash/MD5.py
YekongLib/Crypto/Hash/SHA256.py
YekongLib/Crypto/Hash/SHA384.py
YekongLib/Crypto/Hash/SHA512.py
YekongLib/Crypto/Hash/__init__.py
YekongLib/Crypto/Symmetric/AES128.py
YekongLib/Crypto/Symmetric/AES256.py
YekongLib/Crypto/Symmetric/__init__.py
YekongLib/Network/__init__.py
YekongLib/Yekong/YKUDPServer.py
YekongLib/Yekong/__init__.py