Metadata-Version: 2.1
Name: YekongLib
Version: 1.1.2
Summary: A Python library
Home-page: https://github.com/ZRY551/YekongLib-Python
Author: YELANDAOKONG
Author-email: yelandaokong@yldk.xyz
Classifier: Programming Language :: Python :: 3
Classifier: License :: OSI Approved :: MIT License
Classifier: Operating System :: OS Independent
Requires-Python: >=3.6
License-File: LICENSE.txt
